hcaptcha_challenger/__init__.py
hcaptcha_challenger/models.py
hcaptcha_challenger/utils.py
hcaptcha_challenger/agent/__init__.py
hcaptcha_challenger/agent/challenger.py
hcaptcha_challenger/agent/collector.py
hcaptcha_challenger/agent/exceptions.py
hcaptcha_challenger/cli/__init__.py
hcaptcha_challenger/cli/dataset.py
hcaptcha_challenger/cli/main.py
hcaptcha_challenger/cli/solver.py
hcaptcha_challenger/helper/__init__.py
hcaptcha_challenger/helper/cost_calculator.py
hcaptcha_challenger/helper/create_comparison_image.py
hcaptcha_challenger/helper/create_coordinate_grid.py
hcaptcha_challenger/helper/env_generator.py
hcaptcha_challenger/helper/inject_mouse_visualizer.py
hcaptcha_challenger/helper/mark_element_point.py
hcaptcha_challenger/helper/rasterization.py
hcaptcha_challenger/helper/visualize_attention_points.py
hcaptcha_challenger/helper/webm_to_mp4.py
hcaptcha_challenger/helper/assets/scripts/mouse_visualizer.js
hcaptcha_challenger/skills/__init__.py
hcaptcha_challenger/skills/manager.py
hcaptcha_challenger/skills/rules.yaml
hcaptcha_challenger/skills/schema.py
hcaptcha_challenger/skills/library/drag_connection.md
hcaptcha_challenger/skills/library/drag_object_to_shadow_v1.md
hcaptcha_challenger/skills/library/drag_object_to_shadow_v3_cn.md
hcaptcha_challenger/skills/library/drag_pairs.md
hcaptcha_challenger/skills/library/drag_similar.md
hcaptcha_challenger/skills/library/label_holes.md
hcaptcha_challenger/tools/__init__.py
hcaptcha_challenger/tools/challenge_router/__init__.py
hcaptcha_challenger/tools/challenge_router/challenge_router.md
hcaptcha_challenger/tools/image_classifier/__init__.py
hcaptcha_challenger/tools/image_classifier/image_classifier.md
hcaptcha_challenger/tools/internal/__init__.py
hcaptcha_challenger/tools/internal/base.py
hcaptcha_challenger/tools/internal/providers/__init__.py
hcaptcha_challenger/tools/internal/providers/gemini.py
hcaptcha_challenger/tools/internal/providers/protocol.py
hcaptcha_challenger/tools/spatial/__init__.py
hcaptcha_challenger-0.19.0.dist-info/METADATA
hcaptcha_challenger-0.19.0.dist-info/WHEEL
hcaptcha_challenger-0.19.0.dist-info/entry_points.txt
hcaptcha_challenger-0.19.0.dist-info/licenses/LICENSE
hcaptcha_challenger-0.19.0.dist-info/RECORD
