Metadata-Version: 2.4
Name: hcaptcha-challenger
Version: 0.19.0
Summary: 🥂 Gracefully face hCaptcha challenge with multimodal large language model.
Project-URL: Homepage, https://github.com/QIN2DIM/hcaptcha-challenger
Project-URL: Documentation, https://github.com/QIN2DIM/hcaptcha-challenger
Project-URL: Repository, https://github.com/QIN2DIM/hcaptcha-challenger.git
Project-URL: Issues, https://github.com/QIN2DIM/hcaptcha-challenger/issues
Project-URL: Changelog, https://github.com/QIN2DIM/hcaptcha-challenger/blob/master/CHANGELOG.md
Author-email: QIN2DIM <yaoqinse@gmail.com>, Bingjie Yan <bj.yan.pa@qq.com>
License-Expression: GPL-3.0-or-later
License-File: LICENSE
Keywords: agent,hcaptcha,hcaptcha-challenger,hcaptcha-solver,large language model
Classifier: Development Status :: 3 - Alpha
Classifier: Intended Audience :: Developers
Classifier: Programming Language :: Python :: 3
Classifier: Programming Language :: Python :: 3 :: Only
Classifier: Programming Language :: Python :: 3.10
Classifier: Programming Language :: Python :: 3.11
Classifier: Programming Language :: Python :: 3.12
Classifier: Programming Language :: Python :: 3.13
Classifier: Topic :: Scientific/Engineering :: Artificial Intelligence
Classifier: Topic :: Scientific/Engineering :: Image Processing
Classifier: Topic :: Scientific/Engineering :: Image Recognition
Classifier: Topic :: Software Development
Requires-Python: >=3.10
Requires-Dist: google-genai>=1.56.0
Requires-Dist: httpx[http2]>=0.28.1
Requires-Dist: loguru>=0.7.3
Requires-Dist: matplotlib>=3.10.3
Requires-Dist: msgpack<2.0.0,>=1.1.1
Requires-Dist: opencv-python<5.0,>=4.11.0.88
Requires-Dist: pillow>=11.1.0
Requires-Dist: playwright
Requires-Dist: pydantic-settings>=2.11.0
Requires-Dist: pytz>=2025.2
Requires-Dist: typer>=0.20.0
Provides-Extra: camoufox
Requires-Dist: camoufox[geoip]>=0.4.11; extra == 'camoufox'
Provides-Extra: dataset
Requires-Dist: typer; extra == 'dataset'
Provides-Extra: server
Requires-Dist: fastapi[all]>=0.115.12; extra == 'server'
